<annotation>
    <folder>img</folder>
    <filename>vlcsnap-2023-09-26-16h22m50s060.jpg</filename>
    <size>
        <width>1329</width>
        <height>720</height>
        <depth>3</depth>
    </size>
    <object>
        <name>person</name>
        <pose>Unspecified</pose>
        <truncated>0</truncated>
        <occluded>0</occluded>
        <difficult>0</difficult>
        <bndbox>
            <xmin>642.516968</xmin>
            <ymin>383.468048</ymin>
            <xmax>822.381592</xmax>
            <ymax>507.295837</ymax>
        </bndbox>
    </object>
    <object>
        <name>person</name>
        <pose>Unspecified</pose>
        <truncated>0</truncated>
        <occluded>0</occluded>
        <difficult>0</difficult>
        <bndbox>
            <xmin>580.563599</xmin>
            <ymin>142.802780</ymin>
            <xmax>678.489868</xmax>
            <ymax>267.629150</ymax>
        </bndbox>
    </object>
    <object>
        <name>person</name>
        <pose>Unspecified</pose>
        <truncated>0</truncated>
        <occluded>0</occluded>
        <difficult>0</difficult>
        <bndbox>
            <xmin>418.685486</xmin>
            <ymin>91.873627</ymin>
            <xmax>578.565063</xmax>
            <ymax>260.638885</ymax>
        </bndbox>
    </object>
</annotation>